{
  "$schema": "https://developer.microsoft.com/json-schemas/spfx-build/package-solution.schema.json",
  "solution": {
    "name": "phvb-client-side-solution-prod",
    "id": "869587ed-8ad3-42bd-82c1-ad961ba436c1",
    "version": "1.0.0.4",
    "includeClientSideAssets": true,
    "skipFeatureDeployment": true,
    "isDomainIsolated": false,
    "developer": {
      "name": "",
      "websiteUrl": "",
      "privacyUrl": "",
      "termsOfUseUrl": "",
      "mpnId": "Undefined-1.20.0"
    },
    "metadata": {
      "shortDescription": {
        "default": "phvb description (PROD)"
      },
      "longDescription": {
        "default": "phvb description (PROD)"
      },
      "screenshotPaths": [],
      "videoUrl": "",
      "categories": []
    },
    "webApiPermissionRequests": [
      {
        "resource": "Microsoft Graph",
        "scope": "User.Read"
      },
      {
        "resource": "Microsoft Graph",
        "scope": "User.Read.All"
      }
    ],
    "features": [
      {
        "title": "phvb Feature PROD",
        "description": "The feature that activates elements of the phvb solution for PROD.",
        "id": "738b98c4-40eb-45dc-881a-3bff9f8cf7dd",
        "version": "1.0.0.4"
      }
    ]
  },
  "paths": {
    "zippedPackage": "solution/phvb-prod.sppkg"
  }
}
